tpfd/__init__.py
tpfd/compat.py
tpfd/parser.py
tpfd/rules.py
tpfd-0.2.4.data/data/Test1.txt
tpfd-0.2.4.dist-info/DESCRIPTION.rst
tpfd-0.2.4.dist-info/METADATA
tpfd-0.2.4.dist-info/RECORD
tpfd-0.2.4.dist-info/WHEEL
tpfd-0.2.4.dist-info/metadata.json
tpfd-0.2.4.dist-info/pbr.json
tpfd-0.2.4.dist-info/top_level.txt
