Metadata-Version: 2.0
Name: tpfd
Version: 0.2.4
Summary: Text Parsing Function Dispatcher
Home-page: https://github.com/erinxocon/tpfd
Author: Erin O'Connell
Author-email: erinocon5@gmail.com
License: MIT
Platform: UNKNOWN
Classifier: Intended Audience :: Developers
Classifier: Natural Language :: English
Classifier: Programming Language :: Python
Classifier: Programming Language :: Python :: 2.6
Classifier: Programming Language :: Python :: 2.7
Classifier: Programming Language :: Python :: 3.3
Classifier: Programming Language :: Python :: 3.4
Classifier: Programming Language :: Python :: 3.5
Classifier: Programming Language :: Python :: Implementation :: PyPy
Requires-Dist: parse
